setup.py
doublecheck/__init__.py
doublecheck/gen.py
doublecheck/prop.py
doublecheck.egg-info/PKG-INFO
doublecheck.egg-info/SOURCES.txt
doublecheck.egg-info/dependency_links.txt
doublecheck.egg-info/top_level.txt