Metadata-Version: 1.0
Name: doublecheck
Version: 0.1pre2012-05-08T09-57-27
Summary: Pythonic library for QuickCheck-style randomized testing and SmallCheck-style exhaustive testing of the same test suite.
Home-page: https://github.com/kennknowles/python-doublecheck
Author: Kenn Knowles
Author-email: kenn.knowles@gmail.com
License: Apache 2.0
Platform: UNKNOWN
Classifier: Development Status :: 3 - Alpha
Classifier: Topic :: Software Development :: Testing
Classifier: License :: OSI Approved :: Apache Software License
